{
    "engineering": "工程问题",
    "trip": "行程问题",
    "tree": "植树问题",
    "matrix": "方阵问题",
    "bottle": "空瓶换酒",
    "balance": "天平问题",
    "scissors": "剪绳问题",
    "boat": "过河问题",
    "game": "博弈问题",
    "profit": "经济利润问题",
    "solution": "溶液问题",
    "permutation": "排列组合",
    "probability": "概率问题",
    "exclusion": "容斥原理",
    "maximum": "最值问题",
    "geometry": "几何问题",
    "time": "时间问题",
    "drawer": "抽屉原理",
    "scheduling": "统筹规划",
    "chicken": "鸡兔同笼",
    "cow": "牛吃草问题",
    "count": "计数杂题"
}